mitzi/__init__.py
mitzi/cli.py
mitzi/mitzi.py
mitzi-0.1.0.dist-info/AUTHORS.rst
mitzi-0.1.0.dist-info/LICENSE
mitzi-0.1.0.dist-info/METADATA
mitzi-0.1.0.dist-info/WHEEL
mitzi-0.1.0.dist-info/entry_points.txt
mitzi-0.1.0.dist-info/top_level.txt
mitzi-0.1.0.dist-info/RECORD
