Metadata-Version: 2.1
Name: mitzi
Version: 0.1.0
Summary: Mitzi creates woven images
Home-page: https://github.com/paul-butcher/mitzi
Author: Paul Butcher
Author-email: paul.butcher@gmail.com
License: MIT license
Keywords: mitzi
Platform: UNKNOWN
Classifier: Development Status :: 2 - Pre-Alpha
Classifier: Intended Audience :: Developers
Classifier: License :: OSI Approved :: MIT License
Classifier: Natural Language :: English
Classifier: Programming Language :: Python :: 3
Classifier: Programming Language :: Python :: 3.5
Classifier: Programming Language :: Python :: 3.6
Classifier: Programming Language :: Python :: 3.7
Classifier: Programming Language :: Python :: 3.8
Requires-Python: >=3.5
Requires-Dist: pillow
